{
    "action": "UPDATE",
    "requestData": {
        // These credentials are used for handler operations in the function entrypoint
        // You can use your local credentials with yarn create-event --useAwsEnv
        "callerCredentials": {
            "accessKeyId": "test",
            "secretAccessKey": "test",
            "sessionToken": "testSession"
        },
        // These credentials are used for logging and are not updated as part of default --useAwsEnv
        // You can change the script behavior if you would like this
        "providerCredentials": {
            "accessKeyId": "test",
            "secretAccessKey": "test",
            "sessionToken": "testSession"
        },
        "logicalResourceIdentifier": "MyResource",
        // The desired new state of the model
        "resourceProperties": {
            "Id": "test-example::huh",
            "Name": "huh",
            "Value": "something"
        },
        // The old state of the model when this request was sent
        "previousResourceProperties": {
            "Id": "test-example::huh",
            "Name": "huh",
            "Value": "thing1"
        },
        "stackTags": {},
        "previousStackTags": {},
        "systemTags": {}
    },
    "awsAccountId": "account_id",
    "bearerToken": "bearerToken",
    "region": "us-east-1",
    "stackId": "stack-calling-this",
    "resourceType": "Your::Resource::Here",
    "callbackContext": null,
    "nextToken": null,
    "requestContext": null
}

